{
  "minecraft": {
    "version": "@@MINECRAFT_VERSION@@",
    "modLoaders": [
      {
        "id": "fabric-@@FABRIC_VERSION@@",
        "primary": true
      }
    ]
  },
  "manifestType": "minecraftModpack",
  "manifestVersion": 1,
  "name": "World of Pannotia",
  "version": "@@VERSION@@",
  "author": "cmrcdrm",
  "files": [
    {"projectID": 228525, "fileID": 3753797, "required": true},
    {"projectID": 241119, "fileID": 3567963, "required": true},
    {"projectID": 242064, "fileID": 3671377, "required": true},
    {"projectID": 244260, "fileID": 3671392, "required": true},
    {"projectID": 248787, "fileID": 3686478, "required": true},
    {"projectID": 250419, "fileID": 3754811, "required": true},
    {"projectID": 256717, "fileID": 3757580, "required": true},
    {"projectID": 263420, "fileID": 3811525, "required": true},
    {"projectID": 264738, "fileID": 3213798, "required": true},
    {"projectID": 273279, "fileID": 3687749, "required": true},
    {"projectID": 297318, "fileID": 3528289, "required": true},
    {"projectID": 297344, "fileID": 3783910, "required": true},
    {"projectID": 297818, "fileID": 3542435, "required": true},
    {"projectID": 303119, "fileID": 3692220, "required": true},
    {"projectID": 306612, "fileID": 3817527, "required": true},
    {"projectID": 308702, "fileID": 3789482, "required": true},
    {"projectID": 308769, "fileID": 3764014, "required": true},
    {"projectID": 308892, "fileID": 3783909, "required": true},
    {"projectID": 310111, "fileID": 3816876, "required": true},
    {"projectID": 310205, "fileID": 3755145, "required": true},
    {"projectID": 314579, "fileID": 3755798, "required": true},
    {"projectID": 314633, "fileID": 3707208, "required": true},
    {"projectID": 317121, "fileID": 3668284, "required": true},
    {"projectID": 317780, "fileID": 3811537, "required": true},
    {"projectID": 325092, "fileID": 3709015, "required": true},
    {"projectID": 335493, "fileID": 3606973, "required": true},
    {"projectID": 341888, "fileID": 3668097, "required": true},
    {"projectID": 348521, "fileID": 3782775, "required": true},
    {"projectID": 349239, "fileID": 3725895, "required": true},
    {"projectID": 349240, "fileID": 3764752, "required": true},
    {"projectID": 349630, "fileID": 3667476, "required": true},
    {"projectID": 351393, "fileID": 3551503, "required": true},
    {"projectID": 353890, "fileID": 3758296, "required": true},
    {"projectID": 354339, "fileID": 3697233, "required": true},
    {"projectID": 360438, "fileID": 3801263, "required": true},
    {"projectID": 363104, "fileID": 3687759, "required": true},
    {"projectID": 367561, "fileID": 3345782, "required": true},
    {"projectID": 373591, "fileID": 3793997, "required": true},
    {"projectID": 374274, "fileID": 2934596, "required": true},
    {"projectID": 377281, "fileID": 3796182, "required": true},
    {"projectID": 378266, "fileID": 3779101, "required": true},
    {"projectID": 379680, "fileID": 3763959, "required": true},
    {"projectID": 380393, "fileID": 3680329, "required": true},
    {"projectID": 381257, "fileID": 3773665, "required": true},
    {"projectID": 386175, "fileID": 3692536, "required": true},
    {"projectID": 391366, "fileID": 3820311, "required": true},
    {"projectID": 391911, "fileID": 3541451, "required": true},
    {"projectID": 392254, "fileID": 3687757, "required": true},
    {"projectID": 392805, "fileID": 3549604, "required": true},
    {"projectID": 393236, "fileID": 3809920, "required": true},
    {"projectID": 393442, "fileID": 3541670, "required": true},
    {"projectID": 397434, "fileID": 3793108, "required": true},
    {"projectID": 398502, "fileID": 3544922, "required": true},
    {"projectID": 398652, "fileID": 3769771, "required": true},
    {"projectID": 399798, "fileID": 3573935, "required": true},
    {"projectID": 400322, "fileID": 3684228, "required": true},
    {"projectID": 403815, "fileID": 3687748, "required": true},
    {"projectID": 404870, "fileID": 3672013, "required": true},
    {"projectID": 406550, "fileID": 3629635, "required": true},
    {"projectID": 408481, "fileID": 3780643, "required": true},
    {"projectID": 410896, "fileID": 3708158, "required": true},
    {"projectID": 411557, "fileID": 3543273, "required": true},
    {"projectID": 415758, "fileID": 3692365, "required": true},
    {"projectID": 419699, "fileID": 3807923, "required": true},
    {"projectID": 419938, "fileID": 3545270, "required": true},
    {"projectID": 421649, "fileID": 3779089, "required": true},
    {"projectID": 431698, "fileID": 3800870, "required": true},
    {"projectID": 431823, "fileID": 3693359, "required": true},
    {"projectID": 433518, "fileID": 3209972, "required": true},
    {"projectID": 440979, "fileID": 3791303, "required": true},
    {"projectID": 442278, "fileID": 3550121, "required": true},
    {"projectID": 443476, "fileID": 3717999, "required": true},
    {"projectID": 448233, "fileID": 3743933, "required": true},
    {"projectID": 449328, "fileID": 3594757, "required": true},
    {"projectID": 450922, "fileID": 3706438, "required": true},
    {"projectID": 452046, "fileID": 3717795, "required": true},
    {"projectID": 452768, "fileID": 3550935, "required": true},
    {"projectID": 452832, "fileID": 3602083, "required": true},
    {"projectID": 459857, "fileID": 3767285, "required": true},
    {"projectID": 463113, "fileID": 3680866, "required": true},
    {"projectID": 475358, "fileID": 3637536, "required": true},
    {"projectID": 477078, "fileID": 3709988, "required": true},
    {"projectID": 480684, "fileID": 3778232, "required": true},
    {"projectID": 486080, "fileID": 3699183, "required": true},
    {"projectID": 486778, "fileID": 3555653, "required": true},
    {"projectID": 491407, "fileID": 3548676, "required": true},
    {"projectID": 492295, "fileID": 3778751, "required": true},
    {"projectID": 495059, "fileID": 3602969, "required": true},
    {"projectID": 495267, "fileID": 3810331, "required": true},
    {"projectID": 495453, "fileID": 3515755, "required": true},
    {"projectID": 500525, "fileID": 3684724, "required": true},
    {"projectID": 502516, "fileID": 3545612, "required": true},
    {"projectID": 513840, "fileID": 3806979, "required": true},
    {"projectID": 521427, "fileID": 3697502, "required": true},
    {"projectID": 521783, "fileID": 3667443, "required": true},
    {"projectID": 523776, "fileID": 3567277, "required": true},
    {"projectID": 525586, "fileID": 3777936, "required": true},
    {"projectID": 526606, "fileID": 3704029, "required": true},
    {"projectID": 527334, "fileID": 3641052, "required": true},
    {"projectID": 527350, "fileID": 3542042, "required": true},
    {"projectID": 527685, "fileID": 3693552, "required": true},
    {"projectID": 527781, "fileID": 3542106, "required": true},
    {"projectID": 527908, "fileID": 3542116, "required": true},
    {"projectID": 528272, "fileID": 3542134, "required": true},
    {"projectID": 529593, "fileID": 3542165, "required": true},
    {"projectID": 529942, "fileID": 3542203, "required": true},
    {"projectID": 529954, "fileID": 3542208, "required": true},
    {"projectID": 530057, "fileID": 3542224, "required": true},
    {"projectID": 530225, "fileID": 3542248, "required": true},
    {"projectID": 530648, "fileID": 3542273, "required": true},
    {"projectID": 530816, "fileID": 3549361, "required": true},
    {"projectID": 531265, "fileID": 3542280, "required": true},
    {"projectID": 531270, "fileID": 3542285, "required": true},
    {"projectID": 531272, "fileID": 3542288, "required": true},
    {"projectID": 531305, "fileID": 3542326, "required": true},
    {"projectID": 531351, "fileID": 3675822, "required": true},
    {"projectID": 533006, "fileID": 3664303, "required": true},
    {"projectID": 534489, "fileID": 3694002, "required": true},
    {"projectID": 539610, "fileID": 3542163, "required": true},
    {"projectID": 539614, "fileID": 3542168, "required": true},
    {"projectID": 539824, "fileID": 3542199, "required": true},
    {"projectID": 539830, "fileID": 3542214, "required": true},
    {"projectID": 541191, "fileID": 3542260, "required": true},
    {"projectID": 541198, "fileID": 3654818, "required": true},
    {"projectID": 541214, "fileID": 3672528, "required": true},
    {"projectID": 541470, "fileID": 3669343, "required": true},
    {"projectID": 543652, "fileID": 3543088, "required": true},
    {"projectID": 544912, "fileID": 3807315, "required": true},
    {"projectID": 546841, "fileID": 3570785, "required": true},
    {"projectID": 547429, "fileID": 3804330, "required": true},
    {"projectID": 547434, "fileID": 3671141, "required": true},
    {"projectID": 547471, "fileID": 3671351, "required": true},
    {"projectID": 547689, "fileID": 3658063, "required": true},
    {"projectID": 547700, "fileID": 3550142, "required": true},
    {"projectID": 547861, "fileID": 3568951, "required": true},
    {"projectID": 547881, "fileID": 3810741, "required": true},
    {"projectID": 547964, "fileID": 3542201, "required": true},
    {"projectID": 548708, "fileID": 3727733, "required": true},
    {"projectID": 550889, "fileID": 3568975, "required": true},
    {"projectID": 550966, "fileID": 3675856, "required": true},
    {"projectID": 554277, "fileID": 3778629, "required": true},
    {"projectID": 558914, "fileID": 3768615, "required": true},
    {"projectID": 560280, "fileID": 3717806, "required": true},
    {"projectID": 560323, "fileID": 3665605, "required": true},
    {"projectID": 563525, "fileID": 3687485, "required": true},
    {"projectID": 564870, "fileID": 3723052, "required": true},
    {"projectID": 566140, "fileID": 3813985, "required": true},
    {"projectID": 566798, "fileID": 3606357, "required": true},
    {"projectID": 567172, "fileID": 3608181, "required": true},
    {"projectID": 570431, "fileID": 3669602, "required": true},
    {"projectID": 575588, "fileID": 3670713, "required": true},
    {"projectID": 590988, "fileID": 3777946, "required": true},
    {"projectID": 590990, "fileID": 3778234, "required": true},
    {"projectID": 590993, "fileID": 3777940, "required": true},
    {"projectID": 594052, "fileID": 3822083, "required": true},
    {"projectID": 614336, "fileID": 3783530, "required": true},
    {"projectID": 615134, "fileID": 3773641, "required": true},
    {"projectID": 631020, "fileID": 3818724, "required": true},
    {"projectID": 631403, "fileID": 3820392, "required": true}
  ],
  "overrides": "overrides"
}
